.gitignore
.travis.yml
MANIFEST.in
README.rst
README.txt
bootstrap.py
buildout.cfg
setup.py
travis.cfg
collective/__init__.py
collective.portlet.keywords.egg-info/PKG-INFO
collective.portlet.keywords.egg-info/SOURCES.txt
collective.portlet.keywords.egg-info/dependency_links.txt
collective.portlet.keywords.egg-info/entry_points.txt
collective.portlet.keywords.egg-info/namespace_packages.txt
collective.portlet.keywords.egg-info/not-zip-safe
collective.portlet.keywords.egg-info/requires.txt
collective.portlet.keywords.egg-info/top_level.txt
collective/portlet/__init__.py
collective/portlet/keywords/__init__.py
collective/portlet/keywords/configure.zcml
collective/portlet/keywords/interfaces.py
collective/portlet/keywords/keywords.pt
collective/portlet/keywords/keywords.py
collective/portlet/keywords/upgrades.py
collective/portlet/keywords/upgrades.zcml
collective/portlet/keywords/profiles/default/metadata.xml
collective/portlet/keywords/profiles/default/portlets.xml
docs/HISTORY.txt