Metadata-Version: 1.0
Name: collective.portlet.keywords
Version: 1.0
Summary: Keywords portlet for Plone
Home-page: http://svn.plone.org/svn/collective/
Author: UNKNOWN
Author-email: UNKNOWN
License: GPL
Platform: UNKNOWN
Classifier: Programming Language :: Python
